{
  "team_info": {
    "english_name": "Ivory Coast",
    "city": "Abidjan",
    "founded_year": 1960,
    "stadium": null,
    "capacity": null,
    "market_value": "€525.9M"
  },
  "squad": [
    {
      "name": "法埃",
      "number": null,
      "position": "教练",
      "age": 42,
      "height": 174,
      "weight": 71,
      "preferred_foot": "左右脚",
      "value": null,
      "birth_date": "1984-01-24",
      "nationality": "科特迪瓦",
      "overall_rating": 73,
      "stats": {
        "速度": 71,
        "力量": 79,
        "防守": 70,
        "盘带": 68,
        "传球": 67,
        "射门": 61
      },
      "recent_matches": [],
      "honors": [
        "U17世界杯冠军"
      ],
      "transfers": [
        {
          "date": "2012-02-01",
          "from": "尼斯",
          "to": "退役",
          "fee": "250万欧"
        },
        {
          "date": "2009-01-01",
          "from": "雷丁",
          "to": "尼斯",
          "fee": "350万欧"
        },
        {
          "date": "2007-08-02",
          "from": "南特",
          "to": "雷丁",
          "fee": null
        },
        {
          "date": "2003-07-01",
          "from": "南特B队",
          "to": "南特",
          "fee": null
        }
      ],
      "injuries": [
        {
          "club": "尼斯",
          "injury": "vein occlusion",
          "date": "2011.10.16 – 2012.04.15"
        },
        {
          "club": "尼斯",
          "injury": "vein occlusion",
          "date": "2011.03.11 – 2011.07.10"
        },
        {
          "club": "雷丁",
          "injury": "生病",
          "date": "2008.03.08 – 2008.03.20"
        }
      ],
      "source_url": "https://www.dongqiudi.com/player/50000281"
    },
    {
      "name": "德梅尔",
      "number": null,
      "position": "助理教练",
      "age": 44,
      "height": 180,
      "weight": 93,
      "preferred_foot": "右脚",
      "value": null,
      "birth_date": "1981-06-13",
      "nationality": "科特迪瓦",
      "overall_rating": 67,
      "stats": {
        "速度": 57,
        "力量": 75,
        "防守": 68,
        "盘带": 64,
        "传球": 62,
        "射门": 42
      },
      "recent_matches": [],
      "honors": [
        "德国足球顶级联赛冠军 × 1",
        "酋长杯冠军 × 1"
      ],
      "transfers": [
        {
          "date": "2017-07-01",
          "from": "红星",
          "to": "退役"
        },
        {
          "date": "2017-07-06",
          "from": "马莱康索比特",
          "to": "红星"
        },
        {
          "date": "2016-09-13",
          "from": "自由球员",
          "to": "马莱康索比特"
        },
        {
          "date": "2016-07-01",
          "from": "邓迪联",
          "to": "自由球员"
        },
        {
          "date": "2015-11-23",
          "from": "自由球员",
          "to": "邓迪联"
        },
        {
          "date": "2015-07-01",
          "from": "西汉姆联",
          "to": "自由球员"
        },
        {
          "date": "2011-08-31",
          "from": "汉堡",
          "to": "西汉姆联"
        },
        {
          "date": "2005-07-01",
          "from": "多特蒙德",
          "to": "汉堡"
        },
        {
          "date": "2001-07-01",
          "from": "阿森纳",
          "to": "多特蒙德"
        },
        {
          "date": "2000-08-07",
          "from": "尼姆",
          "to": "阿森纳"
        },
        {
          "date": "1999-07-01",
          "from": "马赛U19",
          "to": "尼姆"
        },
        {
          "date": "1998-07-01",
          "from": "尼姆U19",
          "to": "马赛U19"
        }
      ],
      "injuries": [
        {
          "club": "西汉姆联",
          "injury": "小腿拉伤",
          "date": "2015.04.10 - 2015.06.30"
        },
        {
          "club": "西汉姆联",
          "injury": "胫骨骨折",
          "date": "2012.10.07 - 2012.11.10"
        },
        {
          "club": "汉堡",
          "injury": "腹股沟腿",
          "date": "2010.11.19 - 2010.11.24"
        },
        {
          "club": "汉堡",
          "injury": "淤伤",
          "date": "2009.08.21 - 2009.09.07"
        },
        {
          "club": "汉堡",
          "injury": "大腿问题",
          "date": "2009.03.23 - 2009.04.19"
        },
        {
          "club": "汉堡",
          "injury": "肌肉纤维撕裂",
          "date": "2009.03.02 - 2009.03.20"
        },
        {
          "club": "汉堡",
          "injury": "大腿问题",
          "date": "2009.02.23 - 2009.02.28"
        },
        {
          "club": "汉堡",
          "injury": "拉伤",
          "date": "2007.11.24 - 2007.11.26"
        }
      ],
      "source_url": "https://www.dongqiudi.com/player/50000280"
    },
    {
      "name": "莫里索",
      "number": null,
      "position": "助理教练",
      "age": 65,
      "height": "185cm",
      "weight": null,
      "preferred_foot": null,
      "value": null,
      "birth_date": "1961-04-27",
      "nationality": "法国",
      "overall_rating": null,
      "stats": {
        "速度": null,
        "射门": null,
        "传球": null,
        "盘带": null,
        "防守": null,
        "力量": null
      },
      "recent_matches": [
        {
          "date": "1988-07-01",
          "match": "戛纳 -> 尼斯",
          "score": null,
          "rating": "?",
          "status": null
        },
        {
          "date": "1986-07-01",
          "match": "尼姆 -> 戛纳",
          "score": null,
          "rating": "?",
          "status": null
        },
        {
          "date": "1982-07-01",
          "match": "尼姆U19 -> 尼姆",
          "score": null,
          "rating": null,
          "status": null
        }
      ],
      "source_url": "https://www.dongqiudi.com/player/50177855"
    },
    {
      "name": "海达拉",
      "number": null,
      "position": "助理教练",
      "age": 51,
      "height": null,
      "weight": null,
      "preferred_foot": null,
      "value": null,
      "birth_date": "1974-12-30",
      "nationality": "科特迪瓦",
      "overall_rating": null,
      "stats": null,
      "recent_matches": [],
      "source_url": "https://www.dongqiudi.com/player/50539925"
    },
    {
      "name": "米夏埃尔·法布尔",
      "number": null,
      "position": "守门员教练",
      "age": 41,
      "height": 181,
      "weight": 79,
      "preferred_foot": "右脚",
      "value": null,
      "birth_date": "1984-07-15",
      "nationality": "阿尔及利亚",
      "overall_rating": 64,
      "stats": {
        "扑救": 62,
        "位置": 68,
        "速度": 46,
        "反应": 62,
        "开球": 58,
        "手型": 71
      },
      "recent_matches": [],
      "honors": [
        "U17世界杯冠军",
        "法国全国联赛冠军",
        "阿尔及利亚国家杯冠军"
      ],
      "transfers": [
        {
          "date": "2018-07-01",
          "from": "弗雷瑞斯",
          "to": "退役",
          "type": "退役"
        },
        {
          "date": "2017-07-01",
          "from": "博莱格尼",
          "to": "弗雷瑞斯",
          "type": "免签"
        },
        {
          "date": "2015-07-01",
          "from": "马赛康索拉特",
          "to": "博莱格尼",
          "type": "免签"
        },
        {
          "date": "2015-01-15",
          "from": "自由球员",
          "to": "马赛康索拉特",
          "type": "自由转会"
        },
        {
          "date": "2014-07-01",
          "from": "MC阿尔及尔",
          "to": "自由球员",
          "type": "自由转会"
        },
        {
          "date": "2013-07-01",
          "from": "克莱蒙",
          "to": "MC阿尔及尔",
          "type": "免签"
        },
        {
          "date": "2012-06-30",
          "from": "朗斯",
          "to": "克莱蒙",
          "type": "租借回归"
        },
        {
          "date": "2011-07-15",
          "from": "克莱蒙",
          "to": "朗斯",
          "type": "租借"
        }
      ],
      "youth_transfers": [
        {
          "date": "2003-07-01",
          "from": "佛罗伦萨U19",
          "to": "色当",
          "type": "免签"
        },
        {
          "date": "2002-07-01",
          "from": "博洛尼亚U19",
          "to": "佛罗伦萨U19",
          "type": "免签"
        },
        {
          "date": "2000-07-01",
          "from": "南特B队",
          "to": "博洛尼亚U19",
          "type": "免签"
        }
      ],
      "injuries": [],
      "source_url": "https://www.dongqiudi.com/player/50001071"
    },
    {
      "name": "古阿梅内",
      "number": null,
      "position": "守门员教练",
      "age": 59,
      "height": 183,
      "weight": null,
      "preferred_foot": null,
      "value": null,
      "birth_date": "1966-06-15",
      "nationality": "科特迪瓦",
      "overall_rating": null,
      "stats": {
        "速度": null,
        "射门": null,
        "传球": null,
        "盘带": null,
        "防守": null,
        "力量": null
      },
      "recent_matches": [],
      "source_url": "https://www.dongqiudi.com/player/51122873"
    },
    {
      "name": "阿丁格拉",
      "number": 24,
      "position": "前锋",
      "age": 24,
      "height": 175,
      "weight": 66,
      "preferred_foot": "右脚",
      "value": "100万欧",
      "birth_date": "2002-01-01",
      "nationality": "科特迪瓦",
      "overall_rating": 76,
      "stats": {
        "速度": 87,
        "力量": 54,
        "防守": 50,
        "盘带": 80,
        "传球": 70,
        "射门": 70
      },
      "recent_matches": [
        {
          "date": "05/17",
          "match": "斯特拉斯堡 vs 摩纳哥",
          "score": "5-4",
          "rating": "L",
          "status": "L"
        },
        {
          "date": "05/10",
          "match": "摩纳哥 vs 圣力",
          "score": "0-1",
          "rating": "L",
          "status": "L"
        },
        {
          "date": "05/02",
          "match": "梅斯 vs 摩纳哥",
          "score": "1-2",
          "rating": "W",
          "status": "W"
        },
        {
          "date": "04/25",
          "match": "图卢兹 vs 摩纳哥",
          "score": "2-2",
          "rating": "D",
          "status": "D"
        },
        {
          "date": "04/19",
          "match": "摩纳哥 vs 欧塞尔",
          "score": "2-2",
          "rating": "D",
          "status": "D"
        },
        {
          "date": "04/10",
          "match": "巴黎FC vs 摩纳哥",
          "score": "4-1",
          "rating": "L",
          "status": "L"
        },
        {
          "date": "04/05",
          "match": "摩纳哥 vs 马赛",
          "score": "2-1",
          "rating": "W",
          "status": "W"
        },
        {
          "date": "03/31",
          "match": "苏格兰 vs 科特迪瓦",
          "score": "0-1",
          "rating": "W",
          "status": "W"
        },
        {
          "date": "03/28",
          "match": "友谊赛: 韩国 vs 科特迪瓦",
          "score": "0-4",
          "rating": "W",
          "status": "W"
        },
        {
          "date": "03/22",
          "match": "里昂 vs 摩纳哥",
          "score": "1-2",
          "rating": "W",
          "status": "W"
        },
        {
          "date": "03/14",
          "match": "摩纳哥 vs 布雷斯特",
          "score": "2-0",
          "rating": "W",
          "status": "W"
        },
        {
          "date": "03/06",
          "match": "巴黎圣日耳曼 vs 摩纳哥",
          "score": "1-3",
          "rating": "W",
          "status": "W"
        },
        {
          "date": "02/28",
          "match": "摩纳哥 vs 热那亚",
          "score": "2-0",
          "rating": "W",
          "status": "W"
        },
        {
          "date": "02/25",
          "match": "欧冠: 巴黎圣日耳曼 vs 摩纳哥",
          "score": "2-2",
          "rating": "D",
          "status": "D"
        },
        {
          "date": "02/21",
          "match": "朗斯 vs 摩纳哥",
          "score": "2-3",
          "rating": "W",
          "status": "W"
        }
      ],
      "source_url": "https://www.dongqiudi.com/player/50600608"
    },
    {
      "name": "兰桑",
      "number": 29,
      "position": "前锋",
      "age": 24,
      "height": 185,
      "weight": 79,
      "preferred_foot": "右脚",
      "value": null,
      "birth_date": "2001-07-01",
      "nationality": "科特迪瓦",
      "overall_rating": 78,
      "stats": {
        "速度": 83,
        "力量": 77,
        "防守": 36,
        "盘带": 78,
        "传球": 72,
        "射门": 76
      },
      "recent_matches": [
        {
          "date": "05/27",
          "match": "欧协联 水晶宫 vs 巴列卡诺",
          "score": "1-0",
          "rating": "W",
          "status": "W"
        },
        {
          "date": "05/24",
          "match": "英超 水晶宫 vs 阿森纳",
          "score": "1-2",
          "rating": "L",
          "status": "L"
        },
        {
          "date": "05/17",
          "match": "英超 布伦特福德 vs 水晶宫",
          "score": "2-2",
          "rating": "D",
          "status": "D"
        },
        {
          "date": "04/20",
          "match": "英超 水晶宫 vs 西汉姆联",
          "score": "0-0",
          "rating": "D",
          "status": "D"
        },
        {
          "date": "04/16",
          "match": "欧协联 佛罗伦萨 vs 水晶宫",
          "score": "2-1",
          "rating": "L",
          "status": "L"
        },
        {
          "date": "04/12",
          "match": "英超 水晶宫 vs 纽卡斯尔联",
          "score": "2-1",
          "rating": "W",
          "status": "W"
        },
        {
          "date": "04/09",
          "match": "欧协联 水晶宫 vs 佛罗伦萨",
          "score": "3-0",
          "rating": "W",
          "status": "W"
        },
        {
          "date": "03/31",
          "match": "友谊赛 苏格兰 vs 科特迪瓦",
          "score": "0-1",
          "rating": "W",
          "status": "W"
        },
        {
          "date": "03/28",
          "match": "友谊赛 韩国 vs 科特迪瓦",
          "score": "0-4",
          "rating": "W",
          "status": "W"
        },
        {
          "date": "03/19",
          "match": "欧协联 AEK拉纳卡 vs 水晶宫",
          "score": "1-2",
          "rating": "W",
          "status": "W"
        },
        {
          "date": "03/15",
          "match": "英超 水晶宫 vs 利兹联",
          "score": "5-0",
          "rating": "D",
          "status": "D"
        },
        {
          "date": "03/12",
          "match": "欧协联 水晶宫 vs AEK拉纳卡",
          "score": "0-0",
          "rating": "D",
          "status": "D"
        },
        {
          "date": "03/05",
          "match": "英超 托特纳姆热刺 vs 水晶宫",
          "score": "1-3",
          "rating": "W",
          "status": "W"
        },
        {
          "date": "03/01",
          "match": "英超 曼联 vs 水晶宫",
          "score": "2-1",
          "rating": "L",
          "status": "L"
        },
        {
          "date": "02/26",
          "match": "欧协联 水晶宫 vs 莫斯塔尔日林斯基",
          "score": "2-0",
          "rating": "W",
          "status": "W"
        }
      ],
      "source_url": "https://www.dongqiudi.com/player/50460572"
    },
    {
      "name": "扬·迪奥曼德",
      "number": 49,
      "position": "前锋",
      "age": 19,
      "height": 181,
      "weight": 76,
      "preferred_foot": "右脚",
      "value": null,
      "birth_date": "2006-11-14",
      "nationality": "科特迪瓦",
      "overall_rating": 80,
      "stats": {
        "速度": 91,
        "力量": 62,
        "防守": 39,
        "盘带": 84,
        "传球": 72,
        "射门": 74
      },
      "recent_matches": [
        {
          "date": "05/16",
          "match": "弗赖堡 vs RB莱比锡",
          "score": "4-1",
          "rating": "L",
          "status": "L"
        },
        {
          "date": "05/09",
          "match": "RB莱比锡 vs 圣保利",
          "score": "2-1",
          "rating": "W",
          "status": "W"
        },
        {
          "date": "05/02",
          "match": "勒沃库森 vs RB莱比锡",
          "score": "4-1",
          "rating": "L",
          "status": "L"
        },
        {
          "date": "04/24",
          "match": "RB莱比锡 vs 柏林联合",
          "score": "3-1",
          "rating": "W",
          "status": "W"
        },
        {
          "date": "04/18",
          "match": "法兰克福 vs RB莱比锡",
          "score": "1-3",
          "rating": "W",
          "status": "W"
        },
        {
          "date": "04/11",
          "match": "RB莱比锡 vs 门兴格拉德巴赫",
          "score": "1-0",
          "rating": "W",
          "status": "W"
        },
        {
          "date": "04/04",
          "match": "云达不莱梅 vs RB莱比锡",
          "score": "1-2",
          "rating": "W",
          "status": "W"
        },
        {
          "date": "03/20",
          "match": "RB莱比锡 vs 霍芬海姆",
          "score": "5-0",
          "rating": "W",
          "status": "W"
        },
        {
          "date": "03/15",
          "match": "斯图加特 vs RB莱比锡",
          "score": "1-0",
          "rating": "L",
          "status": "L"
        },
        {
          "date": "03/07",
          "match": "RB莱比锡 vs 奥格斯堡",
          "score": "2-1",
          "rating": "W",
          "status": "W"
        },
        {
          "date": "03/01",
          "match": "汉堡 vs RB莱比锡",
          "score": "1-2",
          "rating": "W",
          "status": "W"
        },
        {
          "date": "02/21",
          "match": "RB莱比锡 vs 多特蒙德",
          "score": "2-2",
          "rating": "D",
          "status": "D"
        },
        {
          "date": "02/15",
          "match": "RB莱比锡 vs 沃尔夫斯堡",
          "score": "2-2",
          "rating": "D",
          "status": "D"
        },
        {
          "date": "02/11",
          "match": "拜仁慕尼黑 vs RB莱比锡",
          "score": "2-0",
          "rating": "L",
          "status": "L"
        },
        {
          "date": "02/08",
          "match": "科隆 vs RB莱比锡",
          "score": "1-2",
          "rating": "W",
          "status": "W"
        }
      ],
      "source_url": "https://www.dongqiudi.com/player/51100200"
    },
    {
      "name": "阿马德·迪亚洛",
      "number": 16,
      "position": "前锋",
      "age": 23,
      "height": 174,
      "weight": 68,
      "preferred_foot": "左脚",
      "value": null,
      "birth_date": "2002-07-11",
      "nationality": "意大利",
      "overall_rating": 80,
      "stats": {
        "速度": 85,
        "力量": 53,
        "防守": 54,
        "盘带": 84,
        "传球": 75,
        "射门": 75
      },
      "recent_matches": [
        {
          "date": "05/14",
          "match": "布莱顿 vs 曼联",
          "score": "0-3",
          "rating": "W",
          "status": "W"
        },
        {
          "date": "05/17",
          "match": "曼联 vs 诺丁汉森林",
          "score": "3-2",
          "rating": "W",
          "status": "W"
        },
        {
          "date": "05/09",
          "match": "桑德兰 vs 曼联",
          "score": "0-0",
          "rating": "D",
          "status": "D"
        },
        {
          "date": "05/03",
          "match": "曼联 vs 利物浦",
          "score": "3-2",
          "rating": "W",
          "status": "W"
        },
        {
          "date": "04/27",
          "match": "曼联 vs 布伦特福德",
          "score": "2-1",
          "rating": "W",
          "status": "W"
        },
        {
          "date": "04/18",
          "match": "切尔西 vs 曼联",
          "score": "0-1",
          "rating": "W",
          "status": "W"
        },
        {
          "date": "04/13",
          "match": "曼联 vs 利兹联",
          "score": "1-2",
          "rating": "L",
          "status": "L"
        },
        {
          "date": "03/31",
          "match": "埃弗顿 vs 科特迪瓦",
          "score": "0-1",
          "rating": "W",
          "status": "W"
        },
        {
          "date": "03/28",
          "match": "科恩 vs 科特迪瓦",
          "score": "5-4",
          "rating": "W",
          "status": "W"
        },
        {
          "date": "03/20",
          "match": "哈德斯菲尔德 vs 曼联",
          "score": "2-3",
          "rating": "W",
          "status": "W"
        },
        {
          "date": "03/15",
          "match": "曼联 vs 阿斯顿维拉",
          "score": "3-1",
          "rating": "W",
          "status": "W"
        },
        {
          "date": "03/04",
          "match": "纽卡斯尔联 vs 曼联",
          "score": "2-1",
          "rating": "L",
          "status": "L"
        },
        {
          "date": "03/01",
          "match": "曼联 vs 水晶宫",
          "score": "2-1",
          "rating": "W",
          "status": "W"
        },
        {
          "date": "02/23",
          "match": "埃弗顿 vs 曼联",
          "score": "0-1",
          "rating": "W",
          "status": "W"
        },
        {
          "date": "02/10",
          "match": "西汉姆联 vs 曼联",
          "score": "1-1",
          "rating": "D",
          "status": "D"
        }
      ],
      "source_url": "https://www.dongqiudi.com/player/50528050"
    },
    {
      "name": "奥马尔·迪亚基特",
      "number": 10,
      "position": "前锋",
      "age": 22,
      "height": 182,
      "weight": 75,
      "preferred_foot": "右脚",
      "value": null,
      "birth_date": "2003-12-20",
      "nationality": "科特迪瓦",
      "overall_rating": 72,
      "stats": {
        "速度": 82,
        "力量": 71,
        "射门": 21,
        "盘带": 70,
        "传球": 57,
        "防守": 71
      },
      "recent_matches": [
        {
          "date": "05/09",
          "match": "拉路维尔 vs 色格拉布鲁日",
          "score": "4-1",
          "rating": "L",
          "status": "L"
        },
        {
          "date": "05/01",
          "match": "色格拉布鲁日 vs 威尔郡",
          "score": "2-3",
          "rating": "L",
          "status": "L"
        },
        {
          "date": "04/24",
          "match": "色格拉布鲁日 vs 普选",
          "score": "2-1",
          "rating": "W",
          "status": "W"
        },
        {
          "date": "04/19",
          "match": "登德 vs 色格拉布鲁日",
          "score": "1-4",
          "rating": "W",
          "status": "W"
        },
        {
          "date": "04/11",
          "match": "色格拉布鲁日 vs 拉路维尔",
          "score": "3-0",
          "rating": "W",
          "status": "W"
        },
        {
          "date": "04/04",
          "match": "威尔郡 vs 色格拉布鲁日",
          "score": "2-2",
          "rating": "D",
          "status": "D"
        },
        {
          "date": "03/22",
          "match": "安德莱赫特 vs 色格拉布鲁日",
          "score": "2-3",
          "rating": "W",
          "status": "W"
        },
        {
          "date": "03/15",
          "match": "色格拉布鲁日 vs 拉路维尔",
          "score": "1-3",
          "rating": "L",
          "status": "L"
        },
        {
          "date": "03/08",
          "match": "圣图尔登 vs 色格拉布鲁日",
          "score": "2-1",
          "rating": "L",
          "status": "L"
        },
        {
          "date": "03/01",
          "match": "色格拉布鲁日 vs 普选",
          "score": "0-0",
          "rating": "D",
          "status": "D"
        },
        {
          "date": "02/07",
          "match": "沙勒鲁瓦 vs 色格拉布鲁日",
          "score": "3-4",
          "rating": "W",
          "status": "W"
        },
        {
          "date": "01/31",
          "match": "色格拉布鲁日 vs 安特卫普",
          "score": "0-4",
          "rating": "L",
          "status": "L"
        },
        {
          "date": "01/25",
          "match": "亨克 vs 色格拉布鲁日",
          "score": "1-1",
          "rating": "D",
          "status": "D"
        },
        {
          "date": "01/17",
          "match": "韦斯特洛 vs 色格拉布鲁日",
          "score": "0-2",
          "rating": "W",
          "status": "W"
        },
        {
          "date": "01/10",
          "match": "埃及 vs 科特迪瓦",
          "score": "3-2",
          "rating": "L",
          "status": "L"
        }
      ],
      "source_url": "https://www.dongqiudi.com/player/50769523"
    },
    {
      "name": "尼古拉·佩佩",
      "number": "19",
      "position": "前锋",
      "age": 28,
      "height": 183,
      "weight": 73,
      "preferred_foot": "右脚",
      "value": "3100万欧元",
      "birth_date": "1995-05-29",
      "nationality": "科特迪瓦",
      "overall_rating": 81,
      "stats": {
        "速度": 87,
        "力量": 89,
        "防守": 57,
        "盘带": 85,
        "传球": 76,
        "射门": 80
      },
      "recent_matches": [
        {
          "date": "05/24",
          "match": "比利亚雷亚尔 vs 马德里竞技",
          "score": "5-1",
          "rating": "W",
          "status": "W"
        },
        {
          "date": "05/17",
          "match": "巴列卡诺 vs 比利亚雷亚尔",
          "score": "2-0",
          "rating": "L",
          "status": "L"
        },
        {
          "date": "05/13",
          "match": "比利亚雷亚尔 vs 塞维利亚",
          "score": "2-3",
          "rating": "L",
          "status": "L"
        },
        {
          "date": "05/10",
          "match": "马略卡 vs 比利亚雷亚尔",
          "score": "1-1",
          "rating": "D",
          "status": "D"
        },
        {
          "date": "05/02",
          "match": "比利亚雷亚尔 vs 塞万提斯",
          "score": "5-1",
          "rating": "W",
          "status": "W"
        },
        {
          "date": "04/26",
          "match": "比利亚雷亚尔 vs 皇家社会",
          "score": "2-1",
          "rating": "W",
          "status": "W"
        },
        {
          "date": "04/23",
          "match": "皇家奥维耶多 vs 比利亚雷亚尔",
          "score": "1-1",
          "rating": "D",
          "status": "D"
        },
        {
          "date": "04/12",
          "match": "毕尔巴鄂竞技 vs 比利亚雷亚尔",
          "score": "1-2",
          "rating": "W",
          "status": "W"
        },
        {
          "date": "04/06",
          "match": "赫罗纳 vs 比利亚雷亚尔",
          "score": "1-0",
          "rating": "L",
          "status": "L"
        },
        {
          "date": "03/31",
          "match": "瓦伦西亚 vs 科特迪瓦",
          "score": "0-1",
          "rating": "W",
          "status": "W"
        },
        {
          "date": "03/28",
          "match": "阿拉维斯 vs 比利亚雷亚尔",
          "score": "0-4",
          "rating": "W",
          "status": "W"
        },
        {
          "date": "03/09",
          "match": "比利亚雷亚尔 vs 皇家社会",
          "score": "3-1",
          "rating": "W",
          "status": "W"
        },
        {
          "date": "03/13",
          "match": "阿拉维斯 vs 比利亚雷亚尔",
          "score": "1-1",
          "rating": "D",
          "status": "D"
        },
        {
          "date": "03/08",
          "match": "比利亚雷亚尔 vs 埃尔切",
          "score": "2-1",
          "rating": "W",
          "status": "W"
        },
        {
          "date": "02/28",
          "match": "巴塞罗那 vs 比利亚雷亚尔",
          "score": "4-1",
          "rating": "L",
          "status": "L"
        }
      ],
      "source_url": "https://www.dongqiudi.com/player/50179915"
    },
    {
      "name": "吉亚贡",
      "number": 10,
      "position": "前锋",
      "age": 23,
      "height": 165,
      "weight": 50,
      "preferred_foot": "右脚",
      "value": null,
      "birth_date": "2001-02-22",
      "nationality": "科特迪瓦",
      "overall_rating": null,
      "stats": {
        "出场": 40,
        "首发": 36,
        "进球": 12,
        "助攻": 5,
        "黄牌": 8,
        "红牌": 0
      },
      "recent_matches": [
        {
          "date": "05/23",
          "match": "杜海利日 vs 沙勒鲁瓦",
          "score": "0-2",
          "rating": "W",
          "status": "W"
        },
        {
          "date": "05/19",
          "match": "沙勒鲁瓦 vs 奥埃瓦里",
          "score": "1-1",
          "rating": "D",
          "status": "D"
        },
        {
          "date": "05/16",
          "match": "沙勒鲁瓦 vs 韦斯特洛",
          "score": "0-1",
          "rating": "L",
          "status": "L"
        },
        {
          "date": "05/10",
          "match": "安特卫普 vs 沙勒鲁瓦",
          "score": "0-1",
          "rating": "W",
          "status": "W"
        },
        {
          "date": "05/02",
          "match": "沙勒鲁瓦 vs 罗克",
          "score": "2-0",
          "rating": "W",
          "status": "W"
        },
        {
          "date": "04/10",
          "match": "沙勒鲁瓦 vs 安特卫普",
          "score": "2-1",
          "rating": "W",
          "status": "W"
        },
        {
          "date": "04/05",
          "match": "韦斯特洛 vs 沙勒鲁瓦",
          "score": "2-0",
          "rating": "L",
          "status": "L"
        },
        {
          "date": "03/21",
          "match": "苏格兰 vs 科特迪瓦",
          "score": "0-1",
          "rating": "W",
          "status": "W"
        },
        {
          "date": "03/08",
          "match": "韩国 vs 科特迪瓦",
          "score": "0-4",
          "rating": "W",
          "status": "W"
        },
        {
          "date": "02/22",
          "match": "威尔郡 vs 沙勒鲁瓦",
          "score": "1-0",
          "rating": "L",
          "status": "L"
        },
        {
          "date": "01/14",
          "match": "沙勒鲁瓦 vs 奥埃瓦里",
          "score": "0-2",
          "rating": "L",
          "status": "L"
        },
        {
          "date": "01/07",
          "match": "登德 vs 沙勒鲁瓦",
          "score": "2-2",
          "rating": "D",
          "status": "D"
        },
        {
          "date": "01/01",
          "match": "沙勒鲁瓦 vs 布鲁日",
          "score": "1-2",
          "rating": "L",
          "status": "L"
        },
        {
          "date": "02/22",
          "match": "韦斯特洛 vs 沙勒鲁瓦",
          "score": "2-1",
          "rating": "L",
          "status": "L"
        },
        {
          "date": "01/14",
          "match": "沙勒鲁瓦 vs 根特",
          "score": "2-3",
          "rating": "L",
          "status": "L"
        }
      ],
      "source_url": "https://www.dongqiudi.com/player/50558497"
    },
    {
      "name": "巴祖马纳·杜尔",
      "number": 29,
      "position": "前锋",
      "age": 20,
      "height": "173cm",
      "weight": "68kg",
      "preferred_foot": "左脚",
      "value": null,
      "birth_date": "2006-03-02",
      "nationality": "科特迪瓦",
      "overall_rating": null,
      "stats": {
        "速度": null,
        "射门": null,
        "传球": null,
        "盘带": null,
        "防守": null,
        "力量": null
      },
      "recent_matches": [
        {
          "date": "05/16",
          "match": "门兴格拉德巴赫 vs 霍芬海姆",
          "score": "4-0",
          "rating": "L",
          "status": "L"
        },
        {
          "date": "05/09",
          "match": "霍芬海姆 vs 云达不莱梅",
          "score": "1-0",
          "rating": "W",
          "status": "W"
        },
        {
          "date": "05/02",
          "match": "霍芬海姆 vs 斯图加特",
          "score": "3-3",
          "rating": "D",
          "status": "D"
        },
        {
          "date": "04/25",
          "match": "汉堡 vs 霍芬海姆",
          "score": "1-2",
          "rating": "W",
          "status": "W"
        },
        {
          "date": "04/18",
          "match": "霍芬海姆 vs 多特蒙德",
          "score": "2-1",
          "rating": "W",
          "status": "W"
        },
        {
          "date": "04/10",
          "match": "奥格斯堡 vs 霍芬海姆",
          "score": "2-2",
          "rating": "D",
          "status": "D"
        },
        {
          "date": "04/04",
          "match": "霍芬海姆 vs 美因茨",
          "score": "1-2",
          "rating": "L",
          "status": "L"
        },
        {
          "date": "03/31",
          "match": "苏格兰 vs 科特迪瓦",
          "score": "0-1",
          "rating": "W",
          "status": "W"
        },
        {
          "date": "03/28",
          "match": "韩国 vs 科特迪瓦",
          "score": "0-4",
          "rating": "W",
          "status": "W"
        },
        {
          "date": "03/20",
          "match": "RB莱比锡 vs 霍芬海姆",
          "score": "5-0",
          "rating": "L",
          "status": "L"
        },
        {
          "date": "03/14",
          "match": "霍芬海姆 vs 沃尔夫斯堡",
          "score": "1-1",
          "rating": "D",
          "status": "D"
        },
        {
          "date": "03/07",
          "match": "海登海姆 vs 霍芬海姆",
          "score": "2-4",
          "rating": "W",
          "status": "W"
        },
        {
          "date": "02/28",
          "match": "霍芬海姆 vs 圣保利",
          "score": "0-1",
          "rating": "L",
          "status": "L"
        },
        {
          "date": "02/21",
          "match": "科隆 vs 霍芬海姆",
          "score": "2-2",
          "rating": "D",
          "status": "D"
        },
        {
          "date": "02/14",
          "match": "霍芬海姆 vs 弗赖堡",
          "score": "3-0",
          "rating": "W",
          "status": "W"
        }
      ],
      "source_url": "https://www.dongqiudi.com/player/50813936"
    },
    {
      "name": "瓦希",
      "number": 11,
      "position": "前锋",
      "age": 23,
      "height": 184,
      "weight": 77,
      "preferred_foot": "右脚",
      "value": null,
      "birth_date": "2003-01-02",
      "nationality": "科特迪瓦",
      "overall_rating": 74,
      "stats": {
        "速度": 84,
        "力量": 65,
        "防守": 31,
        "盘带": 76,
        "传球": 67,
        "射门": 74
      },
      "recent_matches": [
        {
          "date": "05/29",
          "match": "尼斯 vs 圣埃蒂安",
          "score": "4-1",
          "rating": "W",
          "status": "W"
        },
        {
          "date": "05/22",
          "match": "朗斯 vs 尼斯",
          "score": "3-1",
          "rating": "L",
          "status": "L"
        },
        {
          "date": "05/17",
          "match": "尼斯 vs 梅斯",
          "score": "0-0",
          "rating": "D",
          "status": "D"
        },
        {
          "date": "05/10",
          "match": "欧塞尔 vs 尼斯",
          "score": "2-1",
          "rating": "L",
          "status": "L"
        },
        {
          "date": "04/26",
          "match": "马赛 vs 尼斯",
          "score": "1-1",
          "rating": "D",
          "status": "D"
        },
        {
          "date": "04/22",
          "match": "斯特拉斯堡 vs 尼斯",
          "score": "0-2",
          "rating": "W",
          "status": "W"
        },
        {
          "date": "04/19",
          "match": "蒙彼利埃 vs 尼斯",
          "score": "0-0",
          "rating": "D",
          "status": "D"
        },
        {
          "date": "04/12",
          "match": "尼斯 vs 勒阿弗尔",
          "score": "1-1",
          "rating": "D",
          "status": "D"
        },
        {
          "date": "04/04",
          "match": "斯特拉斯堡 vs 尼斯",
          "score": "3-1",
          "rating": "L",
          "status": "L"
        },
        {
          "date": "03/31",
          "match": "苏格兰 vs 科特迪瓦",
          "score": "0-1",
          "rating": "W",
          "status": "W"
        },
        {
          "date": "03/28",
          "match": "韩国 vs 科特迪瓦",
          "score": "0-4",
          "rating": "W",
          "status": "W"
        },
        {
          "date": "03/21",
          "match": "尼斯 vs 巴黎圣日耳曼",
          "score": "0-4",
          "rating": "L",
          "status": "L"
        },
        {
          "date": "03/14",
          "match": "图热 vs 尼斯",
          "score": "0-2",
          "rating": "W",
          "status": "W"
        },
        {
          "date": "03/08",
          "match": "尼斯 vs 雷恩",
          "score": "0-4",
          "rating": "L",
          "status": "L"
        },
        {
          "date": "03/04",
          "match": "洛里昂 vs 尼斯",
          "score": "0-0",
          "rating": "W",
          "status": "W"
        }
      ],
      "source_url": "https://www.dongqiudi.com/player/50489106"
    },
    {
      "name": "博尼",
      "number": 14,
      "position": "前锋",
      "age": 22,
      "height": 189,
      "weight": 86,
      "preferred_foot": "右脚",
      "value": null,
      "birth_date": "2003-10-25",
      "nationality": "科特迪瓦",
      "overall_rating": 78,
      "stats": {
        "速度": 87,
        "力量": 76,
        "防守": 33,
        "盘带": 78,
        "传球": 73,
        "射门": 76
      },
      "recent_matches": [
        {
          "date": "05/23",
          "match": "博洛尼亚 vs 国际米兰",
          "score": "3-3",
          "rating": "D",
          "status": "D"
        },
        {
          "date": "05/17",
          "match": "国际米兰 vs 梅罗纳",
          "score": "1-1",
          "rating": "P",
          "status": "D"
        },
        {
          "date": "05/13",
          "match": "拉齐奥 vs 国际米兰",
          "score": "0-2",
          "rating": "W",
          "status": "W"
        },
        {
          "date": "05/09",
          "match": "拉齐奥 vs 国际米兰",
          "score": "0-3",
          "rating": "W",
          "status": "W"
        },
        {
          "date": "05/03",
          "match": "国际米兰 vs 帕尔马",
          "score": "2-0",
          "rating": "W",
          "status": "W"
        },
        {
          "date": "04/26",
          "match": "都灵 vs 国际米兰",
          "score": "2-2",
          "rating": "D",
          "status": "D"
        },
        {
          "date": "04/21",
          "match": "国际米兰 vs 科莫",
          "score": "3-2",
          "rating": "W",
          "status": "W"
        },
        {
          "date": "04/17",
          "match": "国际米兰 vs 卡利亚里",
          "score": "3-0",
          "rating": "W",
          "status": "W"
        },
        {
          "date": "04/12",
          "match": "科莫 vs 国际米兰",
          "score": "3-4",
          "rating": "W",
          "status": "W"
        },
        {
          "date": "04/05",
          "match": "国际米兰 vs 罗马",
          "score": "5-2",
          "rating": "W",
          "status": "W"
        },
        {
          "date": "03/22",
          "match": "佛罗伦萨 vs 国际米兰",
          "score": "1-1",
          "rating": "D",
          "status": "D"
        },
        {
          "date": "02/14",
          "match": "国际米兰 vs 亚特兰大",
          "score": "1-1",
          "rating": "D",
          "status": "D"
        },
        {
          "date": "03/08",
          "match": "AC米兰 vs 国际米兰",
          "score": "1-0",
          "rating": "L",
          "status": "L"
        },
        {
          "date": "03/03",
          "match": "科莫 vs 国际米兰",
          "score": "0-0",
          "rating": "D",
          "status": "D"
        },
        {
          "date": "02/28",
          "match": "国际米兰 vs 热那亚",
          "score": "2-0",
          "rating": "W",
          "status": "W"
        }
      ],
      "source_url": "https://www.dongqiudi.com/player/50579009"
    },
    {
      "name": "塞科-福法纳",
      "number": null,
      "position": "中场",
      "age": 26,
      "height": 185,
      "weight": 74,
      "preferred_foot": "右脚",
      "value": "700K",
      "birth_date": "1999-05-07",
      "nationality": "科特迪瓦",
      "overall_rating": 76,
      "stats": {
        "速度": 85,
        "力量": 75,
        "防守": 70,
        "盘带": 78,
        "传球": 73,
        "射门": 74
      },
      "recent_matches": [
        {
          "date": "2024/05/26",
          "match": "波尔图 vs 塞韦拉杜",
          "score": "1-0",
          "rating": "7.0",
          "status": "W"
        },
        {
          "date": "2024/05/19",
          "match": "阿维什镇 vs 波尔图",
          "score": "3-1",
          "rating": "6.5",
          "status": "L"
        },
        {
          "date": "2024/05/05",
          "match": "波尔图 vs 阿维斯卡",
          "score": "1-0",
          "rating": "6.8",
          "status": "W"
        },
        {
          "date": "2024/04/26",
          "match": "阿马多拉之星 vs 波尔图",
          "score": "1-2",
          "rating": "7.0",
          "status": "W"
        },
        {
          "date": "2024/04/23",
          "match": "波尔图 vs 曼联(客)",
          "score": "0-0",
          "rating": "6.8",
          "status": "D"
        },
        {
          "date": "2024/04/19",
          "match": "波尔图 vs 通德拉",
          "score": "2-0",
          "rating": "7.0",
          "status": "W"
        },
        {
          "date": "2024/04/16",
          "match": "圣丁戈森林 vs 波尔图",
          "score": "1-0",
          "rating": "6.5",
          "status": "L"
        },
        {
          "date": "2024/04/12",
          "match": "埃斯托里尔 vs 波尔图",
          "score": "1-3",
          "rating": "7.0",
          "status": "W"
        },
        {
          "date": "2024/04/09",
          "match": "波尔图 vs 圣丁戈森林",
          "score": "1-1",
          "rating": "6.8",
          "status": "D"
        },
        {
          "date": "2024/04/04",
          "match": "波尔图 vs 法马利康",
          "score": "2-2",
          "rating": "6.8",
          "status": "D"
        },
        {
          "date": "2024/03/31",
          "match": "本菲卡 vs 科特迪瓦",
          "score": "0-1",
          "rating": "6.8",
          "status": "L"
        },
        {
          "date": "2024/03/28",
          "match": "科恩 vs 科特迪瓦",
          "score": "0-4",
          "rating": "6.5",
          "status": "L"
        },
        {
          "date": "2024/03/22",
          "match": "本菲卡 vs 波尔图",
          "score": "1-2",
          "rating": "6.8",
          "status": "W"
        },
        {
          "date": "2024/03/19",
          "match": "波尔图 vs 莫雷加特",
          "score": "2-0",
          "rating": "7.0",
          "status": "W"
        },
        {
          "date": "2024/03/15",
          "match": "波尔图 vs 莫雷托人",
          "score": "3-0",
          "rating": "6.8",
          "status": "W"
        }
      ],
      "source_url": "https://www.dongqiudi.com/player/50137736"
    },
    {
      "name": "凯西",
      "number": null,
      "position": "中场",
      "age": 29,
      "height": 183,
      "weight": 74,
      "preferred_foot": "右脚",
      "value": null,
      "birth_date": "1996-12-19",
      "nationality": "科特迪瓦",
      "overall_rating": 79,
      "stats": {
        "速度": 73,
        "力量": 86,
        "防守": 77,
        "盘带": 76,
        "传球": 72,
        "射门": 77
      },
      "recent_matches": [
        {
          "date": "05/16",
          "match": "沙特联",
          "score": "3-0",
          "rating": "W",
          "status": "W"
        },
        {
          "date": "05/06",
          "match": "沙特联",
          "score": "3-1",
          "rating": "W",
          "status": "W"
        },
        {
          "date": "05/03",
          "match": "沙特联",
          "score": "4-0",
          "rating": "W",
          "status": "W"
        },
        {
          "date": "04/29",
          "match": "沙特联",
          "score": "2-0",
          "rating": "L",
          "status": "L"
        },
        {
          "date": "04/25",
          "match": "亚冠精英",
          "score": "1-0",
          "rating": "W",
          "status": "W"
        },
        {
          "date": "04/20",
          "match": "亚冠精英",
          "score": "1-2",
          "rating": "W",
          "status": "W"
        },
        {
          "date": "04/17",
          "match": "亚冠精英",
          "score": "2-1",
          "rating": "W",
          "status": "W"
        },
        {
          "date": "04/13",
          "match": "亚冠精英",
          "score": "1-0",
          "rating": "W",
          "status": "W"
        },
        {
          "date": "04/09",
          "match": "沙特联",
          "score": "1-1",
          "rating": "D",
          "status": "D"
        },
        {
          "date": "04/04",
          "match": "沙特联",
          "score": "3-0",
          "rating": "W",
          "status": "W"
        },
        {
          "date": "03/31",
          "match": "友谊赛",
          "score": "0-1",
          "rating": "W",
          "status": "W"
        },
        {
          "date": "03/28",
          "match": "友谊赛",
          "score": "0-4",
          "rating": "W",
          "status": "W"
        },
        {
          "date": "03/18",
          "match": "沙特国王杯",
          "score": "1-1",
          "rating": "L",
          "status": "L"
        },
        {
          "date": "03/13",
          "match": "沙特联",
          "score": "3-2",
          "rating": "L",
          "status": "L"
        },
        {
          "date": "03/06",
          "match": "沙特联",
          "score": "3-1",
          "rating": "W",
          "status": "W"
        }
      ],
      "source_url": "https://www.dongqiudi.com/player/50203958"
    },
    {
      "name": "桑加雷",
      "number": "6",
      "position": "中场",
      "age": 28,
      "height": 191,
      "weight": 77,
      "preferred_foot": "右脚",
      "value": null,
      "birth_date": "1997-12-02",
      "nationality": "科特迪瓦",
      "overall_rating": 78,
      "stats": {
        "速度": 58,
        "力量": 80,
        "防守": 77,
        "盘带": 72,
        "传球": 73,
        "射门": 66
      },
      "recent_matches": [
        {
          "date": "05/24",
          "match": "迈丁汉森林 vs 布里斯托",
          "score": "1-1",
          "rating": "D",
          "status": "D"
        },
        {
          "date": "05/17",
          "match": "曼联 vs 迈丁汉森林",
          "score": "3-2",
          "rating": "L",
          "status": "L"
        },
        {
          "date": "05/07",
          "match": "阿斯顿维拉 vs 迈丁汉森林",
          "score": "4-0",
          "rating": "L",
          "status": "L"
        },
        {
          "date": "04/24",
          "match": "热刺 vs 迈丁汉森林",
          "score": "0-5",
          "rating": "W",
          "status": "W"
        },
        {
          "date": "04/19",
          "match": "迈丁汉森林 vs 布莱顿",
          "score": "4-1",
          "rating": "W",
          "status": "W"
        },
        {
          "date": "04/16",
          "match": "迈丁汉森林 vs 波尔图",
          "score": "1-0",
          "rating": "W",
          "status": "W"
        },
        {
          "date": "04/12",
          "match": "迈丁汉森林 vs 阿斯顿维拉",
          "score": "1-1",
          "rating": "D",
          "status": "D"
        },
        {
          "date": "04/09",
          "match": "波尔图 vs 迈丁汉森林",
          "score": "1-1",
          "rating": "D",
          "status": "D"
        },
        {
          "date": "03/31",
          "match": "苏格兰 vs 科特迪瓦",
          "score": "0-1",
          "rating": "W",
          "status": "W"
        },
        {
          "date": "03/28",
          "match": "韩国 vs 科特迪瓦",
          "score": "0-4",
          "rating": "W",
          "status": "W"
        },
        {
          "date": "03/22",
          "match": "托特纳姆热刺 vs 迈丁汉森林",
          "score": "0-3",
          "rating": "W",
          "status": "W"
        },
        {
          "date": "03/19",
          "match": "毕尔巴鄂 vs 迈丁汉森林",
          "score": "1-2",
          "rating": "W",
          "status": "W"
        },
        {
          "date": "03/15",
          "match": "迈丁汉森林 vs 富勒姆",
          "score": "0-0",
          "rating": "D",
          "status": "D"
        },
        {
          "date": "03/12",
          "match": "迈丁汉森林 vs 中日德兰",
          "score": "0-1",
          "rating": "L",
          "status": "L"
        },
        {
          "date": "03/04",
          "match": "曼城 vs 迈丁汉森林",
          "score": "2-2",
          "rating": "D",
          "status": "D"
        }
      ],
      "source_url": "https://www.dongqiudi.com/player/50239118"
    },
    {
      "name": "塞里",
      "number": "14",
      "position": "中场",
      "age": 34,
      "height": 171,
      "weight": 74,
      "preferred_foot": "右脚",
      "value": null,
      "birth_date": "1991-07-19",
      "nationality": "科特迪瓦",
      "overall_rating": 71,
      "stats": {
        "速度": 56,
        "力量": 62,
        "防守": 65,
        "盘带": 73,
        "传球": 76,
        "射门": 65
      },
      "recent_matches": [
        {
          "date": "05/17",
          "match": "利拉 vs 马里博尔",
          "score": "2-1",
          "rating": "L",
          "status": "L"
        },
        {
          "date": "05/09",
          "match": "马里博尔 vs 卢布尔雅那奥林匹亚",
          "score": "0-1",
          "rating": "L",
          "status": "L"
        },
        {
          "date": "05/03",
          "match": "拉多姆列 vs 马里博尔",
          "score": "2-1",
          "rating": "L",
          "status": "L"
        },
        {
          "date": "04/26",
          "match": "Nk布拉夫 vs 马里博尔",
          "score": "3-0",
          "rating": "L",
          "status": "L"
        },
        {
          "date": "04/18",
          "match": "马里博尔 vs 普里莫捷",
          "score": "2-0",
          "rating": "W",
          "status": "W"
        },
        {
          "date": "04/14",
          "match": "科佩尔 vs 马里博尔",
          "score": "3-1",
          "rating": "L",
          "status": "L"
        },
        {
          "date": "04/04",
          "match": "采列 vs 马里博尔",
          "score": "1-0",
          "rating": "L",
          "status": "L"
        },
        {
          "date": "03/31",
          "match": "苏格兰 vs 科特迪瓦",
          "score": "0-1",
          "rating": "W",
          "status": "W"
        },
        {
          "date": "03/29",
          "match": "戈塔普 vs 科特迪瓦",
          "score": "0-4",
          "rating": "W",
          "status": "W"
        },
        {
          "date": "03/20",
          "match": "塞拉利 vs 马里博尔",
          "score": "1-1",
          "rating": "D",
          "status": "D"
        },
        {
          "date": "03/14",
          "match": "马里博尔 vs 伊拉",
          "score": "3-0",
          "rating": "W",
          "status": "W"
        },
        {
          "date": "03/08",
          "match": "卢布尔雅那奥林匹亚 vs 马里博尔",
          "score": "0-0",
          "rating": "D",
          "status": "D"
        },
        {
          "date": "02/28",
          "match": "马里博尔 vs 拉多姆列",
          "score": "2-2",
          "rating": "D",
          "status": "D"
        },
        {
          "date": "02/22",
          "match": "马里博尔 vs NK布拉夫",
          "score": "2-0",
          "rating": "W",
          "status": "W"
        },
        {
          "date": "02/15",
          "match": "普里莫捷 vs 马里博尔",
          "score": "0-2",
          "rating": "W",
          "status": "W"
        }
      ],
      "source_url": "https://www.dongqiudi.com/player/50111723"
    },
    {
      "name": "乌拉伊",
      "number": 42,
      "position": "中场",
      "age": 20,
      "height": 173,
      "weight": 63,
      "preferred_foot": "右脚",
      "value": null,
      "birth_date": "2006-04-06",
      "nationality": "科特迪瓦",
      "overall_rating": 68,
      "stats": {
        "速度": 75,
        "力量": 63,
        "防守": 62,
        "盘带": 74,
        "传球": 67,
        "射门": 56,
        "国际声望": 1,
        "进攻能力": 2,
        "花式技巧": 2
      },
      "recent_matches": [
        {
          "date": "05/22",
          "match": "特拉布宗体育 vs 科尼亚体育",
          "score": "2-1",
          "rating": "W",
          "status": "W"
        },
        {
          "date": "05/17",
          "match": "特拉布宗体育 vs 青年联合",
          "score": "0-3",
          "rating": "L",
          "status": "L"
        },
        {
          "date": "05/13",
          "match": "青年联合 vs 特拉布宗体育",
          "score": "1-2",
          "rating": "W",
          "status": "W"
        },
        {
          "date": "05/09",
          "match": "贝西克塔斯 vs 特拉布宗体育",
          "score": "1-2",
          "rating": "W",
          "status": "W"
        },
        {
          "date": "05/02",
          "match": "特拉布宗体育 vs 班兹塔比",
          "score": "1-1",
          "rating": "D",
          "status": "D"
        },
        {
          "date": "04/27",
          "match": "科尼亚体育 vs 特拉布宗体育",
          "score": "2-1",
          "rating": "L",
          "status": "L"
        },
        {
          "date": "04/23",
          "match": "伊姆轮体育 vs 特拉布宗体育",
          "score": "0-0",
          "rating": "-",
          "status": "-"
        },
        {
          "date": "04/19",
          "match": "特拉布宗体育 vs RAMS巴萨克赛尔",
          "score": "1-1",
          "rating": "D",
          "status": "D"
        },
        {
          "date": "04/11",
          "match": "阿拉尼亚体育 vs 特拉布宗体育",
          "score": "1-1",
          "rating": "D",
          "status": "D"
        },
        {
          "date": "03/31",
          "match": "苏格兰 vs 科特迪瓦",
          "score": "0-1",
          "rating": "L",
          "status": "L"
        },
        {
          "date": "03/28",
          "match": "韩国 vs 科特迪瓦",
          "score": "0-4",
          "rating": "W",
          "status": "W"
        },
        {
          "date": "03/18",
          "match": "埃于普体育 vs 特拉布宗体育",
          "score": "0-1",
          "rating": "W",
          "status": "W"
        },
        {
          "date": "03/14",
          "match": "特拉布宗体育 vs 里泽体育",
          "score": "1-0",
          "rating": "W",
          "status": "W"
        },
        {
          "date": "03/09",
          "match": "开塞利体育 vs 特拉布宗体育",
          "score": "1-3",
          "rating": "W",
          "status": "W"
        },
        {
          "date": "03/03",
          "match": "RAMS巴萨克赛尔 vs 特拉布宗体育",
          "score": "2-4",
          "rating": "W",
          "status": "W"
        }
      ],
      "source_url": "https://www.dongqiudi.com/player/51000925"
    },
    {
      "name": "阿格巴杜",
      "number": 12,
      "position": "后卫",
      "age": 28,
      "height": 192,
      "weight": 86,
      "preferred_foot": "右脚",
      "value": "1500万欧",
      "birth_date": "1997-06-17",
      "nationality": "科特迪瓦",
      "overall_rating": 77,
      "stats": {
        "速度": 80,
        "力量": 82,
        "防守": 76,
        "盘带": 66,
        "传球": 63,
        "射门": 50
      },
      "recent_matches": [
        {
          "date": "05/15",
          "match": "重庆体育 vs 贝西克塔斯",
          "score": "2-2",
          "rating": "D",
          "status": "D"
        },
        {
          "date": "05/09",
          "match": "贝西克塔斯 vs 特拉布宗体育",
          "score": "1-2",
          "rating": "L",
          "status": "L"
        },
        {
          "date": "05/05",
          "match": "土耳其杯",
          "score": "0-1",
          "rating": "L",
          "status": "L"
        },
        {
          "date": "05/01",
          "match": "加济安泰普 vs 科尼亚体育",
          "score": "0-2",
          "rating": "W",
          "status": "W"
        },
        {
          "date": "04/27",
          "match": "贝西克塔斯 vs 卡拉居姆吕克",
          "score": "0-0",
          "rating": "D",
          "status": "D"
        },
        {
          "date": "04/23",
          "match": "贝西克塔斯 vs 阿拉尼亚体育",
          "score": "3-0",
          "rating": "W",
          "status": "W"
        },
        {
          "date": "04/19",
          "match": "萨姆松体育 vs 贝西克塔斯",
          "score": "2-1",
          "rating": "L",
          "status": "L"
        },
        {
          "date": "04/10",
          "match": "贝西克塔斯 vs 安塔利亚体育",
          "score": "4-2",
          "rating": "W",
          "status": "W"
        },
        {
          "date": "04/05",
          "match": "费内巴切 vs 贝西克塔斯",
          "score": "1-0",
          "rating": "L",
          "status": "L"
        },
        {
          "date": "03/31",
          "match": "友谊赛",
          "score": "0-1",
          "rating": "W",
          "status": "W"
        },
        {
          "date": "03/28",
          "match": "友谊赛",
          "score": "0-4",
          "rating": "W",
          "status": "W"
        },
        {
          "date": "03/19",
          "match": "土超",
          "score": "2-1",
          "rating": "W",
          "status": "W"
        },
        {
          "date": "03/15",
          "match": "土超",
          "score": "0-2",
          "rating": "W",
          "status": "W"
        },
        {
          "date": "03/07",
          "match": "土超",
          "score": "0-1",
          "rating": "L",
          "status": "L"
        },
        {
          "date": "03/04",
          "match": "土超",
          "score": "4-1",
          "rating": "W",
          "status": "W"
        }
      ],
      "source_url": "https://www.dongqiudi.com/player/50518792"
    },
    {
      "name": "辛戈",
      "number": 90,
      "position": "后卫",
      "age": 25,
      "height": 190,
      "weight": 79,
      "preferred_foot": "右脚",
      "value": null,
      "birth_date": "2000-12-25",
      "nationality": "科特迪瓦",
      "overall_rating": 79,
      "stats": {
        "速度": 80,
        "力量": 83,
        "防守": 79,
        "盘带": 74,
        "传球": 68,
        "射门": 61
      },
      "recent_matches": [
        {
          "date": "05/17",
          "match": "卡希梅萨 vs 加拉塔萨雷",
          "score": "1-0",
          "rating": "L",
          "status": "L"
        },
        {
          "date": "05/09",
          "match": "加拉塔萨雷 vs 安塔利亚体育",
          "score": "4-2",
          "rating": "W",
          "status": "W"
        },
        {
          "date": "05/02",
          "match": "伊斯坦布尔 vs 加拉塔萨雷",
          "score": "4-1",
          "rating": "L",
          "status": "L"
        },
        {
          "date": "04/26",
          "match": "加拉塔萨雷 vs 青年联合",
          "score": "3-0",
          "rating": "W",
          "status": "W"
        },
        {
          "date": "04/22",
          "match": "土耳其杯",
          "score": "0-2",
          "rating": "L",
          "status": "L"
        },
        {
          "date": "04/18",
          "match": "青年联合 vs 加拉塔萨雷",
          "score": "1-2",
          "rating": "W",
          "status": "W"
        },
        {
          "date": "04/12",
          "match": "加拉塔萨雷 vs 科贾埃利体育",
          "score": "1-1",
          "rating": "D",
          "status": "D"
        },
        {
          "date": "04/08",
          "match": "哥兹塔比 vs 加拉塔萨雷",
          "score": "1-3",
          "rating": "W",
          "status": "W"
        },
        {
          "date": "04/04",
          "match": "特拉布宗体育 vs 加拉塔萨雷",
          "score": "2-1",
          "rating": "L",
          "status": "L"
        },
        {
          "date": "03/31",
          "match": "苏格兰 vs 科特迪瓦",
          "score": "0-1",
          "rating": "W",
          "status": "W"
        },
        {
          "date": "03/28",
          "match": "科隆 vs 科特迪瓦",
          "score": "0-4",
          "rating": "W",
          "status": "W"
        },
        {
          "date": "03/18",
          "match": "利物浦 vs 加拉塔萨雷",
          "score": "4-0",
          "rating": "L",
          "status": "L"
        },
        {
          "date": "03/14",
          "match": "加拉塔萨雷 vs RAMS巴萨克赛尔",
          "score": "3-0",
          "rating": "W",
          "status": "W"
        },
        {
          "date": "03/10",
          "match": "加拉塔萨雷 vs 利物浦",
          "score": "1-0",
          "rating": "W",
          "status": "W"
        },
        {
          "date": "03/07",
          "match": "贝西克塔斯 vs 加拉塔萨雷",
          "score": "0-1",
          "rating": "W",
          "status": "W"
        }
      ],
      "source_url": "https://www.dongqiudi.com/player/50491157"
    },
    {
      "name": "科南",
      "number": 3,
      "position": "后卫",
      "age": 30,
      "height": 176,
      "weight": 71,
      "preferred_foot": "左脚",
      "value": null,
      "birth_date": "1995-12-27",
      "nationality": "吉尔维森特",
      "overall_rating": 73,
      "stats": {
        "速度": 79,
        "力量": 74,
        "防守": 69,
        "盘带": 69,
        "传球": 66,
        "射门": 51
      },
      "recent_matches": [
        {
          "date": "05/16",
          "match": "葡萄牙体育 vs 吉尔维森特",
          "score": "3-0",
          "rating": "L",
          "status": "L"
        },
        {
          "date": "05/11",
          "match": "吉尔维森特 vs 阿罗卡",
          "score": "1-3",
          "rating": "L",
          "status": "L"
        },
        {
          "date": "05/03",
          "match": "阿维河 vs 吉尔维森特",
          "score": "0-0",
          "rating": "D",
          "status": "D"
        },
        {
          "date": "04/18",
          "match": "吉尔维森特 vs 吉马良斯",
          "score": "0-1",
          "rating": "L",
          "status": "L"
        },
        {
          "date": "04/13",
          "match": "通德拉 vs 吉尔维森特",
          "score": "2-2",
          "rating": "D",
          "status": "D"
        },
        {
          "date": "04/03",
          "match": "吉尔维森特 vs 阿维什镇",
          "score": "3-0",
          "rating": "W",
          "status": "W"
        },
        {
          "date": "03/31",
          "match": "苏维达 vs 科特迪瓦",
          "score": "0-1",
          "rating": "W",
          "status": "W"
        },
        {
          "date": "03/28",
          "match": "科隆 vs 科特迪瓦",
          "score": "0-4",
          "rating": "W",
          "status": "W"
        },
        {
          "date": "03/21",
          "match": "圣克拉拉 vs 吉尔维森特",
          "score": "1-0",
          "rating": "L",
          "status": "L"
        },
        {
          "date": "03/14",
          "match": "吉尔维森特 vs 阿维卡",
          "score": "2-2",
          "rating": "D",
          "status": "D"
        },
        {
          "date": "03/08",
          "match": "阿马多拉之星 vs 吉尔维森特",
          "score": "2-2",
          "rating": "D",
          "status": "D"
        },
        {
          "date": "03/02",
          "match": "吉尔维森特 vs 本菲卡",
          "score": "1-2",
          "rating": "L",
          "status": "L"
        },
        {
          "date": "02/22",
          "match": "埃斯托里尔 vs 吉尔维森特",
          "score": "3-1",
          "rating": "L",
          "status": "L"
        },
        {
          "date": "02/14",
          "match": "吉尔维森特 vs 布拉加",
          "score": "2-1",
          "rating": "W",
          "status": "W"
        },
        {
          "date": "02/07",
          "match": "莫雷拉人 vs 吉尔维森特",
          "score": "1-2",
          "rating": "W",
          "status": "W"
        }
      ],
      "source_url": "https://www.dongqiudi.com/player/50256795"
    },
    {
      "name": "盖拉·杜埃",
      "number": 22,
      "position": "后卫",
      "age": 23,
      "height": 187,
      "weight": 84,
      "preferred_foot": "右脚",
      "value": null,
      "birth_date": "2002-10-17",
      "nationality": "科特迪瓦",
      "overall_rating": 77,
      "stats": {
        "速度": 72,
        "力量": 78,
        "防守": 75,
        "盘带": 72,
        "传球": 71,
        "射门": 52
      },
      "recent_matches": [
        {
          "date": "05/17",
          "match": "斯特拉斯堡 vs 摩纳哥",
          "score": "5-4",
          "rating": "W",
          "status": "W"
        },
        {
          "date": "05/13",
          "match": "布雷斯特 vs 斯特拉斯堡",
          "score": "1-2",
          "rating": "W",
          "status": "W"
        },
        {
          "date": "05/10",
          "match": "昂热 vs 斯特拉斯堡",
          "score": "1-1",
          "rating": "D",
          "status": "D"
        },
        {
          "date": "05/07",
          "match": "斯特拉斯堡 vs 巴列卡诺",
          "score": "0-1",
          "rating": "L",
          "status": "L"
        },
        {
          "date": "04/19",
          "match": "斯特拉斯堡 vs 雷恩",
          "score": "0-3",
          "rating": "L",
          "status": "L"
        },
        {
          "date": "04/16",
          "match": "斯特拉斯堡 vs 英国茨",
          "score": "4-0",
          "rating": "W",
          "status": "W"
        },
        {
          "date": "04/09",
          "match": "美因茨 vs 斯特拉斯堡",
          "score": "2-0",
          "rating": "L",
          "status": "L"
        },
        {
          "date": "04/04",
          "match": "斯特拉斯堡 vs 尼斯",
          "score": "3-1",
          "rating": "W",
          "status": "W"
        },
        {
          "date": "03/31",
          "match": "苏格兰 vs 科特迪瓦",
          "score": "0-1",
          "rating": "W",
          "status": "W"
        },
        {
          "date": "03/28",
          "match": "友谊赛",
          "score": "0-4",
          "rating": "W",
          "status": "W"
        },
        {
          "date": "03/22",
          "match": "南特 vs 斯特拉斯堡",
          "score": "2-3",
          "rating": "W",
          "status": "W"
        },
        {
          "date": "03/19",
          "match": "斯特拉斯堡 vs 里耶卡",
          "score": "1-1",
          "rating": "D",
          "status": "D"
        },
        {
          "date": "03/15",
          "match": "斯特拉斯堡 vs 巴黎FC",
          "score": "0-0",
          "rating": "D",
          "status": "D"
        },
        {
          "date": "03/12",
          "match": "里耶卡 vs 斯特拉斯堡",
          "score": "1-2",
          "rating": "W",
          "status": "W"
        },
        {
          "date": "03/07",
          "match": "波塞尔 vs 斯特拉斯堡",
          "score": "0-0",
          "rating": "D",
          "status": "D"
        }
      ],
      "source_url": "https://www.dongqiudi.com/player/50526750"
    },
    {
      "name": "恩迪卡",
      "number": "4",
      "position": "后卫",
      "age": 26,
      "height": 192,
      "weight": 82,
      "preferred_foot": "左脚",
      "value": null,
      "birth_date": "1999-08-20",
      "nationality": "科特迪瓦",
      "overall_rating": 81,
      "stats": {
        "速度": 74,
        "力量": 82,
        "防守": 82,
        "盘带": 69,
        "传球": 69,
        "射门": 53
      },
      "recent_matches": [
        {
          "date": "05/17",
          "match": "罗马 vs 拉齐奥",
          "score": "2-0",
          "rating": "W",
          "status": "W"
        },
        {
          "date": "05/10",
          "match": "帕尔马 vs 罗马",
          "score": "2-3",
          "rating": "W",
          "status": "W"
        },
        {
          "date": "05/04",
          "match": "罗马 vs 维罗纳",
          "score": "4-0",
          "rating": "W",
          "status": "W"
        },
        {
          "date": "04/21",
          "match": "博洛尼亚 vs 罗马",
          "score": "0-2",
          "rating": "W",
          "status": "W"
        },
        {
          "date": "04/18",
          "match": "罗马 vs 亚特兰大",
          "score": "1-1",
          "rating": "D",
          "status": "D"
        },
        {
          "date": "04/10",
          "match": "罗马 vs 比萨",
          "score": "3-0",
          "rating": "W",
          "status": "W"
        },
        {
          "date": "04/05",
          "match": "国际米兰 vs 罗马",
          "score": "5-2",
          "rating": "L",
          "status": "L"
        },
        {
          "date": "03/31",
          "match": "苏维托 vs 科林蒂安",
          "score": "0-1",
          "rating": "W",
          "status": "W"
        },
        {
          "date": "03/28",
          "match": "友谊赛",
          "score": "8-4",
          "rating": "W",
          "status": "W"
        },
        {
          "date": "03/22",
          "match": "罗马 vs 美伦",
          "score": "1-0",
          "rating": "W",
          "status": "W"
        },
        {
          "date": "03/19",
          "match": "欧联",
          "score": "3-4",
          "rating": "L",
          "status": "L"
        },
        {
          "date": "03/15",
          "match": "意甲",
          "score": "2-1",
          "rating": "L",
          "status": "L"
        },
        {
          "date": "03/12",
          "match": "欧联",
          "score": "1-1",
          "rating": "D",
          "status": "D"
        },
        {
          "date": "03/08",
          "match": "意甲",
          "score": "2-1",
          "rating": "L",
          "status": "L"
        },
        {
          "date": "03/01",
          "match": "意甲",
          "score": "3-3",
          "rating": "D",
          "status": "D"
        }
      ],
      "source_url": "https://www.dongqiudi.com/player/50267835"
    },
    {
      "name": "奥迪隆·科苏努",
      "number": 3,
      "position": "后卫",
      "age": 25,
      "height": 191,
      "weight": 79,
      "preferred_foot": "右脚",
      "value": null,
      "birth_date": "2001-01-04",
      "nationality": "科特迪瓦",
      "overall_rating": 80,
      "stats": {
        "速度": 80,
        "力量": 78,
        "防守": 81,
        "盘带": 67,
        "传球": 64,
        "射门": 32
      },
      "recent_matches": [
        {
          "date": "05/19",
          "match": "AC米兰 vs 塞特拉大",
          "score": "2-3",
          "rating": "W",
          "status": "L"
        },
        {
          "date": "05/02",
          "match": "塞特拉大 vs 热那亚",
          "score": "0-0",
          "rating": "D",
          "status": "D"
        },
        {
          "date": "04/27",
          "match": "卡利亚里 vs 塞特拉大",
          "score": "3-2",
          "rating": "L",
          "status": "L"
        },
        {
          "date": "04/22",
          "match": "塞特拉大 vs 拉齐奥",
          "score": "1-1",
          "rating": "L",
          "status": "D"
        },
        {
          "date": "04/18",
          "match": "罗马 vs 塞特拉大",
          "score": "1-1",
          "rating": "D",
          "status": "D"
        },
        {
          "date": "04/11",
          "match": "塞特拉大 vs 尤文图斯",
          "score": "0-1",
          "rating": "L",
          "status": "L"
        },
        {
          "date": "04/06",
          "match": "莱切 vs 塞特拉大",
          "score": "0-3",
          "rating": "W",
          "status": "W"
        },
        {
          "date": "03/31",
          "match": "苏格兰 vs 科特迪瓦",
          "score": "0-1",
          "rating": "W",
          "status": "W"
        },
        {
          "date": "03/28",
          "match": "友谊赛",
          "score": "0-4",
          "rating": "W",
          "status": "L"
        },
        {
          "date": "03/22",
          "match": "塞特拉大 vs 维罗纳",
          "score": "1-0",
          "rating": "W",
          "status": "W"
        },
        {
          "date": "03/18",
          "match": "萨勒尼塔纳 vs 塞特拉大",
          "score": "4-1",
          "rating": "L",
          "status": "L"
        },
        {
          "date": "03/14",
          "match": "国际米兰 vs 塞特拉大",
          "score": "1-1",
          "rating": "D",
          "status": "D"
        },
        {
          "date": "03/10",
          "match": "塞特拉大 vs 拉齐奥",
          "score": "1-6",
          "rating": "L",
          "status": "L"
        },
        {
          "date": "03/07",
          "match": "塞特拉大 vs 乌迪内斯",
          "score": "2-2",
          "rating": "D",
          "status": "D"
        },
        {
          "date": "03/04",
          "match": "拉齐奥 vs 塞特拉大",
          "score": "2-2",
          "rating": "D",
          "status": "D"
        }
      ],
      "source_url": "https://www.dongqiudi.com/player/50483316"
    },
    {
      "name": "迪奥曼德",
      "number": 26,
      "position": "后卫",
      "age": 22,
      "height": 190,
      "weight": 93,
      "preferred_foot": "右脚",
      "value": null,
      "birth_date": "2001-12-04",
      "nationality": "科特迪瓦",
      "overall_rating": 80,
      "stats": {
        "速度": 80,
        "力量": 86,
        "防守": 79,
        "盘带": 70,
        "传球": 51,
        "射门": 26
      },
      "recent_matches": [
        {
          "date": "05/24",
          "match": "葡萄牙体育 vs 托里什人联合",
          "score": "1-2",
          "rating": "L",
          "status": "L"
        },
        {
          "date": "05/11",
          "match": "阿维河 vs 葡萄牙体育",
          "score": "1-4",
          "rating": "W",
          "status": "W"
        },
        {
          "date": "05/04",
          "match": "葡萄牙体育 vs 吉马良斯",
          "score": "5-1",
          "rating": "W",
          "status": "W"
        },
        {
          "date": "04/29",
          "match": "葡萄牙体育 vs 通德拉",
          "score": "2-2",
          "rating": "D",
          "status": "D"
        },
        {
          "date": "04/26",
          "match": "阿维什镇 vs 葡萄牙体育",
          "score": "1-1",
          "rating": "D",
          "status": "D"
        },
        {
          "date": "04/22",
          "match": "波尔图 vs 葡萄牙体育",
          "score": "0-0",
          "rating": "D",
          "status": "D"
        },
        {
          "date": "04/19",
          "match": "葡萄牙体育 vs 本菲卡",
          "score": "1-2",
          "rating": "L",
          "status": "L"
        },
        {
          "date": "04/15",
          "match": "阿森纳 vs 葡萄牙体育",
          "score": "0-0",
          "rating": "D",
          "status": "D"
        },
        {
          "date": "04/11",
          "match": "阿马多拉之星 vs 葡萄牙体育",
          "score": "0-1",
          "rating": "W",
          "status": "W"
        },
        {
          "date": "04/07",
          "match": "葡萄牙体育 vs 阿森纳",
          "score": "0-1",
          "rating": "L",
          "status": "L"
        },
        {
          "date": "04/03",
          "match": "葡萄牙体育 vs 圣克拉拉",
          "score": "4-2",
          "rating": "W",
          "status": "W"
        },
        {
          "date": "03/31",
          "match": "苏格兰 vs 科特迪瓦",
          "score": "0-1",
          "rating": "W",
          "status": "W"
        },
        {
          "date": "03/28",
          "match": "埃因霍温 vs 科特迪瓦",
          "score": "0-4",
          "rating": "W",
          "status": "W"
        },
        {
          "date": "03/22",
          "match": "阿德卡 vs 葡萄牙体育",
          "score": "1-4",
          "rating": "W",
          "status": "W"
        },
        {
          "date": "03/17",
          "match": "葡萄牙体育 vs 哈德斯菲尔德",
          "score": "5-0",
          "rating": "W",
          "status": "W"
        }
      ],
      "source_url": "https://www.dongqiudi.com/player/50770150"
    },
    {
      "name": "克里斯托弗·奥佩里",
      "number": 21,
      "position": "前锋",
      "age": 29,
      "height": 183,
      "weight": 78,
      "preferred_foot": "左脚",
      "value": null,
      "birth_date": "1997-04-29",
      "nationality": "科特迪瓦",
      "overall_rating": 74,
      "stats": {
        "速度": 78,
        "力量": 72,
        "防守": 68,
        "盘带": 72,
        "传球": 70,
        "射门": 81
      },
      "recent_matches": [
        {
          "date": "05/16",
          "match": "加济安泰普 vs RAMS巴萨克赛尔",
          "score": "1-2",
          "rating": "W",
          "status": "W"
        },
        {
          "date": "05/09",
          "match": "RAMS巴萨克赛尔 vs 伊斯坦体育",
          "score": "3-0",
          "rating": "W",
          "status": "W"
        },
        {
          "date": "04/11",
          "match": "RAMS巴萨克赛尔 vs 青年联合",
          "score": "3-0",
          "rating": "W",
          "status": "W"
        },
        {
          "date": "04/06",
          "match": "科贾埃利体育 vs RAMS巴萨克赛尔",
          "score": "0-0",
          "rating": "D",
          "status": "D"
        },
        {
          "date": "03/07",
          "match": "RAMS巴萨克赛尔 vs 阿达纳19",
          "score": "2-1",
          "rating": "W",
          "status": "W"
        },
        {
          "date": "03/03",
          "match": "RAMS巴萨克赛尔 vs 特拉布宗体育",
          "score": "2-4",
          "rating": "L",
          "status": "L"
        },
        {
          "date": "02/27",
          "match": "阿拉尼亚体育 vs RAMS巴萨克赛尔",
          "score": "2-0",
          "rating": "W",
          "status": "W"
        },
        {
          "date": "02/21",
          "match": "阿拉尼亚体育 vs RAMS巴萨克赛尔",
          "score": "1-2",
          "rating": "W",
          "status": "W"
        },
        {
          "date": "02/15",
          "match": "RAMS巴萨克赛尔 vs 贝西克塔斯",
          "score": "2-3",
          "rating": "L",
          "status": "L"
        },
        {
          "date": "02/08",
          "match": "埃于普体育 vs RAMS巴萨克赛尔",
          "score": "1-2",
          "rating": "W",
          "status": "W"
        },
        {
          "date": "02/04",
          "match": "卡拉比埃克 vs RAMS巴萨克赛尔",
          "score": "1-4",
          "rating": "W",
          "status": "W"
        },
        {
          "date": "01/31",
          "match": "RAMS巴萨克赛尔 vs 塞泽体育",
          "score": "2-2",
          "rating": "D",
          "status": "D"
        },
        {
          "date": "01/24",
          "match": "开塞利体育 vs RAMS巴萨克赛尔",
          "score": "0-3",
          "rating": "W",
          "status": "W"
        },
        {
          "date": "01/17",
          "match": "RAMS巴萨克赛尔 vs 卡拉居姆吕克",
          "score": "2-1",
          "rating": "W",
          "status": "W"
        },
        {
          "date": "01/13",
          "match": "RAMS巴萨克赛尔 vs 博卢体育",
          "score": "2-1",
          "rating": "W",
          "status": "W"
        }
      ],
      "source_url": "https://www.dongqiudi.com/player/50224845"
    },
    {
      "name": "叶海亚·福法纳",
      "number": 75,
      "position": "门将",
      "age": 25,
      "height": 194,
      "weight": 89,
      "preferred_foot": "右脚",
      "value": null,
      "birth_date": "2000-08-21",
      "nationality": "科特迪瓦",
      "overall_rating": 74,
      "stats": {
        "扑救": 75,
        "位置": 72,
        "速度": 41,
        "反应": 75,
        "开球": 70,
        "手型": 71
      },
      "recent_matches": [
        {
          "date": "05/15",
          "match": "里泽体育 vs 贡西奥塔斯",
          "score": "2-2",
          "rating": "P",
          "status": "D"
        },
        {
          "date": "05/09",
          "match": "埃于普体育 vs 里泽体育",
          "score": "4-0",
          "rating": "L",
          "status": "L"
        },
        {
          "date": "05/01",
          "match": "里泽体育 vs 科尼亚体育",
          "score": "3-2",
          "rating": "W",
          "status": "W"
        },
        {
          "date": "04/25",
          "match": "开塞利体育 vs 里泽体育",
          "score": "2-0",
          "rating": "L",
          "status": "L"
        },
        {
          "date": "04/17",
          "match": "费内巴切 vs 里泽体育",
          "score": "2-2",
          "rating": "P",
          "status": "D"
        },
        {
          "date": "04/13",
          "match": "里泽体育 vs 加济安泰普",
          "score": "2-1",
          "rating": "W",
          "status": "W"
        },
        {
          "date": "04/09",
          "match": "里泽体育 vs 伊斯坦布",
          "score": "4-1",
          "rating": "W",
          "status": "W"
        },
        {
          "date": "04/05",
          "match": "卡拉皮姆吕克 vs 里泽体育",
          "score": "2-1",
          "rating": "L",
          "status": "L"
        },
        {
          "date": "03/31",
          "match": "苏格兰 vs 科特迪瓦",
          "score": "0-1",
          "rating": "W",
          "status": "W"
        },
        {
          "date": "03/28",
          "match": "韩国 vs 科特迪瓦",
          "score": "0-4",
          "rating": "W",
          "status": "W"
        },
        {
          "date": "03/14",
          "match": "特拉布宗体育 vs 里泽体育",
          "score": "1-0",
          "rating": "L",
          "status": "L"
        },
        {
          "date": "03/08",
          "match": "里泽体育 vs 安塔利亚体育",
          "score": "1-0",
          "rating": "W",
          "status": "W"
        },
        {
          "date": "03/04",
          "match": "贝西克塔斯 vs 里泽体育",
          "score": "4-1",
          "rating": "L",
          "status": "L"
        },
        {
          "date": "02/28",
          "match": "卡斯帕萨 vs 里泽体育",
          "score": "0-3",
          "rating": "W",
          "status": "W"
        },
        {
          "date": "02/20",
          "match": "里泽体育 vs 科贾埃利体育",
          "score": "2-0",
          "rating": "W",
          "status": "W"
        }
      ],
      "source_url": "https://www.dongqiudi.com/player/50263312"
    },
    {
      "name": "拉冯",
      "number": 40,
      "position": "门将",
      "age": 27,
      "height": 196,
      "weight": 90,
      "preferred_foot": "右脚",
      "value": null,
      "birth_date": "1999-01-23",
      "nationality": "科特迪瓦",
      "overall_rating": 74,
      "stats": {
        "扑救": 71,
        "位置": 75,
        "速度": 47,
        "反应": 79,
        "传球": 69,
        "手型": 70
      },
      "recent_matches": [
        {
          "date": "05/17",
          "match": "帕纳辛奈科斯 vs 塞萨洛尼基",
          "score": "2-2",
          "rating": "D",
          "status": "D"
        },
        {
          "date": "05/13",
          "match": "奥林匹亚科斯 vs 帕纳辛奈科斯",
          "score": "1-0",
          "rating": "L",
          "status": "L"
        },
        {
          "date": "05/10",
          "match": "雅典AEK vs 帕纳辛奈科斯",
          "score": "2-1",
          "rating": "L",
          "status": "L"
        },
        {
          "date": "05/03",
          "match": "帕纳辛奈科斯 vs 雅典AEK",
          "score": "0-0",
          "rating": "D",
          "status": "D"
        },
        {
          "date": "04/19",
          "match": "帕纳辛奈科斯 vs 拉科尼亚",
          "score": "0-2",
          "rating": "L",
          "status": "L"
        },
        {
          "date": "04/05",
          "match": "塞萨洛尼基 vs 帕纳辛奈科斯",
          "score": "0-0",
          "rating": "D",
          "status": "D"
        },
        {
          "date": "03/31",
          "match": "苏格兰 vs 科特迪瓦",
          "score": "0-1",
          "rating": "W",
          "status": "W"
        },
        {
          "date": "03/28",
          "match": "韩国 vs 科特迪瓦",
          "score": "0-4",
          "rating": "W",
          "status": "W"
        },
        {
          "date": "03/22",
          "match": "阿斯特拉斯特里波利斯 vs 帕纳辛奈科斯",
          "score": "1-2",
          "rating": "W",
          "status": "W"
        },
        {
          "date": "03/19",
          "match": "皇家贝蒂斯 vs 帕纳辛奈科斯",
          "score": "4-0",
          "rating": "L",
          "status": "L"
        },
        {
          "date": "03/15",
          "match": "帕纳辛奈科斯 vs 帕纳托利克斯",
          "score": "0-0",
          "rating": "D",
          "status": "D"
        },
        {
          "date": "03/12",
          "match": "帕纳辛奈科斯 vs 波罗茨南斯",
          "score": "1-0",
          "rating": "W",
          "status": "W"
        },
        {
          "date": "03/08",
          "match": "莱瓦贾科斯 vs 帕纳辛奈科斯",
          "score": "1-4",
          "rating": "W",
          "status": "W"
        },
        {
          "date": "03/04",
          "match": "帕纳辛奈科斯 vs CF克恩特",
          "score": "4-1",
          "rating": "W",
          "status": "W"
        },
        {
          "date": "03/01",
          "match": "帕纳辛奈科斯 vs 阿里斯",
          "score": "3-1",
          "rating": "W",
          "status": "W"
        }
      ],
      "source_url": "https://www.dongqiudi.com/player/50251299"
    },
    {
      "name": "穆罕默德·科内",
      "number": 30,
      "position": "门将",
      "age": 24,
      "height": 186,
      "weight": 78,
      "preferred_foot": "右脚",
      "value": null,
      "birth_date": "2000-03-07",
      "nationality": "科特迪瓦",
      "overall_rating": 68,
      "stats": {
        "扑救": 66,
        "位置": 64,
        "速度": 31,
        "反应": 70,
        "开球": 64,
        "手型": 66
      },
      "recent_matches": [
        {
          "date": "06/23",
          "match": "标准列日 vs 沙勒鲁瓦",
          "score": "0-2",
          "rating": "W",
          "status": "W"
        },
        {
          "date": "05/19",
          "match": "沙勒鲁瓦 vs 奥地利",
          "score": "1-1",
          "rating": "D",
          "status": "D"
        },
        {
          "date": "05/16",
          "match": "沙勒鲁瓦 vs 韦斯特洛",
          "score": "0-1",
          "rating": "L",
          "status": "L"
        },
        {
          "date": "05/10",
          "match": "安特卫普 vs 沙勒鲁瓦",
          "score": "0-1",
          "rating": "W",
          "status": "W"
        },
        {
          "date": "05/02",
          "match": "沙勒鲁瓦 vs 亨克",
          "score": "2-0",
          "rating": "W",
          "status": "W"
        },
        {
          "date": "04/25",
          "match": "奥哈瓦斯 vs 沙勒鲁瓦",
          "score": "0-2",
          "rating": "W",
          "status": "W"
        },
        {
          "date": "04/21",
          "match": "亨克 vs 沙勒鲁瓦",
          "score": "1-1",
          "rating": "D",
          "status": "D"
        },
        {
          "date": "04/18",
          "match": "沙勒鲁瓦 vs 标准列日",
          "score": "1-2",
          "rating": "L",
          "status": "L"
        },
        {
          "date": "04/10",
          "match": "沙勒鲁瓦 vs 安特卫普",
          "score": "2-1",
          "rating": "W",
          "status": "W"
        },
        {
          "date": "04/05",
          "match": "韦斯特洛 vs 沙勒鲁瓦",
          "score": "2-0",
          "rating": "L",
          "status": "L"
        },
        {
          "date": "03/31",
          "match": "苏格兰 vs 科特迪瓦",
          "score": "0-1",
          "rating": "W",
          "status": "W"
        },
        {
          "date": "03/28",
          "match": "友谊赛",
          "score": "0-4",
          "rating": "W",
          "status": "W"
        },
        {
          "date": "03/22",
          "match": "威尔郡 vs 沙勒鲁瓦",
          "score": "1-0",
          "rating": "L",
          "status": "L"
        },
        {
          "date": "03/14",
          "match": "沙勒鲁瓦 vs 奥地利",
          "score": "0-2",
          "rating": "L",
          "status": "L"
        },
        {
          "date": "03/07",
          "match": "登德 vs 沙勒鲁瓦",
          "score": "2-2",
          "rating": "D",
          "status": "D"
        }
      ],
      "source_url": "https://www.dongqiudi.com/player/50658379"
    }
  ],
  "schedule": [
    {
      "date": "1/7 03:00",
      "competition": "非洲杯",
      "home_team": "科特迪瓦",
      "away_team": "布基纳法索",
      "score": "3 - 0"
    },
    {
      "date": "1/11 03:00",
      "competition": "非洲杯",
      "home_team": "埃及",
      "away_team": "科特迪瓦",
      "score": "3 - 2"
    },
    {
      "date": "3/28 22:00",
      "competition": "友谊赛",
      "home_team": "韩国",
      "away_team": "科特迪瓦",
      "score": "0 - 4"
    },
    {
      "date": "4/1 02:30",
      "competition": "友谊赛",
      "home_team": "苏格兰",
      "away_team": "科特迪瓦",
      "score": "0 - 1"
    },
    {
      "date": "6/5 03:10",
      "competition": "友谊赛",
      "home_team": "法国",
      "away_team": "科特迪瓦",
      "score": null
    },
    {
      "date": "6/26 04:00",
      "competition": "世界杯",
      "home_team": "库拉索",
      "away_team": "科特迪瓦",
      "score": null
    }
  ]
}